pyngo/__init__.py
pyngo/errors.py
pyngo/openapi.py
pyngo/py.typed
pyngo/querydict.py
pyngo-2.4.1.dist-info/METADATA
pyngo-2.4.1.dist-info/WHEEL
pyngo-2.4.1.dist-info/licenses/LICENSE
pyngo-2.4.1.dist-info/RECORD
