Metadata-Version: 2.4
Name: pyngo
Version: 2.4.1
Summary: Pydantic Package for Adding Models into a Django or Django Rest Framework Project ✨
Project-URL: Homepage, https://github.com/yezz123/pyngo
Project-URL: Funding, https://github.com/sponsors/yezz123
Author-email: Yasser Tahiri <hello@yezz.me>
License-Expression: MIT
License-File: LICENSE
Keywords: django,django-rest-framework,pydantic,pydantic-django,pydantic-models
Classifier: Framework :: Django
Classifier: Intended Audience :: Developers
Classifier: Intended Audience :: Information Technology
Classifier: License :: OSI Approved :: MIT License
Classifier: Natural Language :: English
Classifier: Operating System :: OS Independent
Classifier: Programming Language :: Python
Classifier: Programming Language :: Python :: 3 :: Only
Classifier: Programming Language :: Python :: 3.10
Classifier: Programming Language :: Python :: 3.11
Classifier: Programming Language :: Python :: 3.12
Classifier: Programming Language :: Python :: 3.13
Classifier: Topic :: Internet :: WWW/HTTP :: Session
Classifier: Typing :: Typed
Requires-Python: >=3.10
Requires-Dist: django<6.0.0,>=3.2.0
Requires-Dist: pydantic<2.13.0,>=2.8.2
Requires-Dist: typing-extensions<4.16.0,>=3.7.4
